lppydsmc/__init__.py
lppydsmc/system_creator.py
lppydsmc/data/__init__.py
lppydsmc/data/disk_space.py
lppydsmc/data/saver.py
lppydsmc/plotting/__init__.py
lppydsmc/plotting/analysis.py
lppydsmc/plotting/matplotlib_utils.py
lppydsmc/utils/__init__.py
lppydsmc/utils/advector.py
lppydsmc/utils/collider.py
lppydsmc/utils/grid.py
lppydsmc/utils/injector.py
lppydsmc/utils/particle.py
lppydsmc/utils/physics.py
lppydsmc/utils/schemes.py
lppydsmc/utils/systems.py
lppydsmc/utils/wall_collision.py
lppydsmc_taltos-0.0.4.dist-info/LICENSE
lppydsmc_taltos-0.0.4.dist-info/METADATA
lppydsmc_taltos-0.0.4.dist-info/WHEEL
lppydsmc_taltos-0.0.4.dist-info/top_level.txt
lppydsmc_taltos-0.0.4.dist-info/RECORD
