Metadata-Version: 2.1
Name: lppydsmc-taltos
Version: 0.0.4
Summary: small DSMC tool written in python
Home-page: https://github.com/PaulCalot/lppydsmc
Author: Paul Calot
Author-email: paul.calot@hotmail.fr
License: UNKNOWN
Project-URL: Bug Tracker, https://github.com/PaulCalot/lppydsmc/issues
Platform: UNKNOWN
Classifier: Programming Language :: Python :: 3
Classifier: License :: OSI Approved :: MIT License
Classifier: Operating System :: OS Independent
Requires-Python: >=3.7
License-File: LICENSE
